README.md
setup.py
json_paginator/__init__.py
json_paginator.egg-info/PKG-INFO
json_paginator.egg-info/SOURCES.txt
json_paginator.egg-info/dependency_links.txt
json_paginator.egg-info/requires.txt
json_paginator.egg-info/top_level.txt