Metadata-Version: 2.1
Name: json-paginator
Version: 0.1.0
Summary: A generator for iterating over paginated JSON API responses
Home-page: https://github.com/chris48s/json-paginator
Author: chris48s
License: MIT
Platform: UNKNOWN
Classifier: License :: OSI Approved :: MIT License
Classifier: Programming Language :: Python
Classifier: Programming Language :: Python :: 3
